bianca_project/__init__.py
bianca_project/bianca.py
Bianca_first_project-0.1.0.dist-info/METADATA
Bianca_first_project-0.1.0.dist-info/WHEEL
Bianca_first_project-0.1.0.dist-info/top_level.txt
Bianca_first_project-0.1.0.dist-info/RECORD
