Metadata-Version: 2.1
Name: Bianca-first-project
Version: 0.1.0
Summary: first Project
Home-page: UNKNOWN
Author: Oprea Bianca
Author-email: biancaoprea33@yahoo.com
License: UNKNOWN
Platform: UNKNOWN
